<?xml version="1.0" encoding="UTF-8"?>
<messages xmlns="https://www.news.admin.ch/messages" xmlns:xsi="http://www.w3.org/2001/XMLSchema-instance" version="1.0">
  <message id="36956" revoked="no">
    <version>5</version>
    <pubdate>2010-12-22</pubdate>
    <type>Memorandum</type>
    <originator department-msg="no" id="806" lead="yes" topnews="no">
      <department-id>801</department-id>
      <name lang="de">Bundesamt für Zivilluftfahrt</name>
      <name lang="fr">Office fédéral de l'aviation civile</name>
      <name lang="it">Ufficio federale dell'aviazione civile</name>
      <name lang="en">Federal Office of Civil Aviation</name>
      <www lang="de">http://www.bazl.admin.ch</www>
      <www lang="fr">http://www.bazl.admin.ch</www>
      <www lang="it">http://www.bazl.admin.ch</www>
      <www lang="en">http://www.bazl.admin.ch</www>
      <email lang="de">info@bazl.admin.ch</email>
      <email lang="fr">info@bazl.admin.ch</email>
      <email lang="it">info@bazl.admin.ch</email>
      <email lang="en">info@bazl.admin.ch</email>
    </originator>
    <department id="801">
      <name lang="de">Eidgenössisches Departement für Umwelt, Verkehr, Energie und Kommunikation</name>
      <name lang="fr">Département fédéral de l'environnement, des transports, de l'énergie et de la communication</name>
      <name lang="it">Dipartimento federale dell'ambiente, dei trasporti, dell'energia e delle comunicazioni</name>
      <name lang="en">Federal Department of the Environment, Transport, Energy and Communications</name>
      <www lang="de">https://www.uvek.admin.ch/uvek/de/home.html</www>
      <www lang="fr">https://www.uvek.admin.ch/uvek/fr/home.html</www>
      <www lang="it">https://www.uvek.admin.ch/uvek/it/home.html</www>
      <www lang="en">https://www.uvek.admin.ch/uvek/en/home.html</www>
      <email lang="de">info@gs-uvek.admin.ch</email>
      <email lang="fr">info@gs-uvek.admin.ch</email>
      <email lang="it">info@gs-uvek.admin.ch</email>
      <email lang="en">info@gs-uvek.admin.ch</email>
    </department>
    <content lang="de">
      <city>Bern</city>
      <title>Piloten beim Anflug nach Samedan unterstützen</title>
      <teaser>Der Flugplatz Samedan führt für Piloten, die künftig nach Samedan fliegen wollen, die Pflicht ein, einen Einweisungsflug zu absolvieren, um mit den lokalen Gegebenheiten besser vertraut zu werden. Zudem müssen Piloten vor einem Flug nach Samedan ein elektronisches Briefing durchführen. Weiter braucht es als Voraussetzung für Anflüge mit Jet- und mehrmotorigen Flugzeugen eine minimale Sicht von fünf Kilometern und eine Wolkenuntergrenze, die nicht tiefer als 700 Metern über Grund liegt. Das BAZL hat diese Auflagen in Absprache mit dem Flugplatz festgelegt. Dabei handelt es sich um eine Vorsichtsmassnahme nach verschiedenen Unfällen in den vergangenen Jahren.</teaser>
      <lead>Der Flugplatz Samedan führt für Piloten, die künftig nach Samedan fliegen wollen, die Pflicht ein, einen Einweisungsflug zu absolvieren, um mit den lokalen Gegebenheiten besser vertraut zu werden. Zudem müssen Piloten vor einem Flug nach Samedan ein elektronisches Briefing durchführen. Weiter braucht es als Voraussetzung für Anflüge mit Jet- und mehrmotorigen Flugzeugen eine minimale Sicht von fünf Kilometern und eine Wolkenuntergrenze, die nicht tiefer als 700 Metern über Grund liegt. Das BAZL hat diese Auflagen in Absprache mit dem Flugplatz festgelegt. Dabei handelt es sich um eine Vorsichtsmassnahme nach verschiedenen Unfällen in den vergangenen Jahren.</lead>
      <text link="no">&lt;p&gt;Am vergangenen Sonntag stürzte ein Jet-Flugzeug, das sich im Anflug auf den Flugplatz Samedan befand, bei Bever ab. Das Flugzeug wurde zerstört und die beiden Piloten kamen ums Leben. Aufgrund seiner Höhe und der gebirgigen Umgebung stellt ein Anflug auf den Flugplatz Samedan höhere Anforderungen an die Piloten als ein Flugplatz im Flachland. Mit Blick auf diesen Umstand und auf Grund mehrerer Unfälle in den vergangenen Jahren hat das BAZL in Absprache und im Einverständnis mit dem Flugplatz beschlossen, für Piloten einen Einweisungsflug vorzuschreiben. Durch einen solchen Flug unter Aufsicht eines Experten können sich die Piloten mit den Verhältnissen rund um den Flugplatz Samaden besser vertraut machen. Die Umsetzung dieser Vorgabe wird Anfang nächsten Jahres an die Hand genommen.&lt;/p&gt; &lt;p&gt;Weiter gilt als Voraussetzung für einen Anflug mit Jet- und mehrmotorigen Flugzeugen in Samedan eine Mindestsicht von fünf Kilometern und eine Wolkenuntergrenze von 2200 Fuss (knapp 700 Meter) über Grund. Bis anhin war es möglich, Anflüge unter bestimmten Umständen bis zu einer minimalen Sicht von 1,5 km durchzuführen. Diese Regelung tritt am 23. Dezember 2010 in Kraft.&lt;/p&gt; &lt;p&gt;Diese Massnahmen haben präventiven Charakter und lassen keine definitiven Rückschlüsse auf die Ursache des Unfalls vom letzten Sonntag zu. Diese wird durch das Büro für Flugunfalluntersuchungen (BFU) abgeklärt.&lt;/p&gt; &lt;p&gt;Nach einem Unfall im Februar 2009, bei dem ein Flugzeug in eine Schneemauer neben der Piste geprallt war, hat das BAZL verschiedene Massnahmen zur Verbesserung der Flugsicherheit in die Wege geleitet. Um die Piloten besser auf die besondere Situation in Samedan vorzubereiten, verlangte das Amt unter anderem, dass den Piloten alle wichtigen Informationen über den Anflug auf Internet zur Verfügung gestellt werden. Die Unterlagen für ein solches Briefing sind inzwischen auf der Website des Flugplatzes aufgeschaltet. Weitere Massnahmen um die Sicherheit zu stärken und den Anliegen der Region zu entsprechen, befinden sich in Vorbereitung. Dabei geht es unter anderem um Anpassungen an den Flugwegen und den Ausbau der optischen Hilfen für Anflüge nach Samedan.&lt;/p&gt;</text>
      <contact/>
      <revisions>
        <revision date="2010-12-23 08:31" type="R"/>
        <revision date="2010-12-22 15:41" type="R"/>
      </revisions>
    </content>
    <content lang="fr">
      <city>Berne</city>
      <title>Assistance pour les pilotes atterrissant à Samedan</title>
      <teaser>A la suite de plusieurs accidents survenus ces dernières années, l’OFAC a décrété en accord avec l’aérodrome de Samedan diverses mesures de précaution. Ainsi, les pilotes qui prévoient de se poser à l’aérodrome de Samedan devront dorénavant suivre un vol d’initiation afin de se familiariser avec les conditions locales. De plus, avant tout vol à destination de Samedan, ces mêmes pilotes devront effectuer un briefing assisté par ordinateur. Enfin, les avions à réaction et les avions multimoteur ne pourront at-terrir que si la visibilité horizontale atteint au moins 5 km et que la base des nuages se trouve à une hauteur de 700 m ou plus.</teaser>
      <lead>A la suite de plusieurs accidents survenus ces dernières années, l’OFAC a décrété en accord avec l’aérodrome de Samedan diverses mesures de précaution. Ainsi, les pilotes qui prévoient de se poser à l’aérodrome de Samedan devront dorénavant suivre un vol d’initiation afin de se familiariser avec les conditions locales. De plus, avant tout vol à destination de Samedan, ces mêmes pilotes devront effectuer un briefing assisté par ordinateur. Enfin, les avions à réaction et les avions multimoteur ne pourront at-terrir que si la visibilité horizontale atteint au moins 5 km et que la base des nuages se trouve à une hauteur de 700 m ou plus.</lead>
      <text link="no">&lt;p&gt;Un avion à réaction s'est écrasé dimanche dernier à Bever alors qu'il tentait d'atterrir sur l'aérodrome de Samedan. L'appareil a été entièrement détruit et les deux pilotes qui se trouvaient aux commandes ont trouvé la mort. Situé en altitude dans un décor de montagnes, l'aérodrome grison est plus exigeant pour les pilotes qu'un aérodrome de plaine. Cette caractéristique, conjuguée au fait que plusieurs accidents se sont produits ces dernières années dans la région, a conduit l'OFAC, en accord avec l'aérodrome, à imposer aux pilotes un vol d'initiation en compagnie d'un expert destiné à les familiariser avec l'environnement de Samedan. Cette mesure sera mise en œuvre dès le début de l'année prochaine.&lt;/p&gt; &lt;p&gt;Actuellement, les atterrissages sont possibles dans certaines circonstances avec une visibilité horizontale de 1,5 km. Il a maintenant été décidé que les avions à réaction et les avions multimoteur ne pourront dorénavant atterrir à Samedan qu'à condition que la visibilité horizontale atteigne au moins 5 km et que la base des nuages se situe à une hauteur de 2200 pieds ou plus (près de 700 mètres). Cette réglementation entre en vigueur le 23 décembre 2010.&lt;/p&gt; &lt;p&gt;Ces mesures ont un caractère préventif et ne sauraient en rien préjuger des conclusions définitives de l'enquête menée par le Bureau d'enquêtes sur les accidents d'aviation (BEAA) sur les causes de l'accident survenu dimanche dernier.&lt;/p&gt; &lt;p&gt;A la suite d'un accident survenu en février 2009 au cours duquel un avion avait percuté un amas de neige en bordure de piste, l'OFAC avait ordonné plusieurs mesures afin d'améliorer la sécurité aérienne. Dans le souci de préparer au mieux les pilotes aux conditions particulières de Samedan, l'office avait notamment exigé de mettre à la disposition des pilotes via Internet toutes les informations utiles pour les manœuvres d'atterrissage. La documentation correspondante figure désormais sur le site Internet de l'aérodrome. D'autres mesures visant à renforcer la sécurité tout en satisfaisant les intérêts de la région sont en préparation. Ces mesures portent notamment sur une modification des trajectoires de vol et le développement des aides visuelles pour l'approche sur Samedan.&lt;/p&gt;</text>
      <contact/>
      <revisions>
        <revision date="2010-12-23 08:31" type="R"/>
      </revisions>
    </content>
    <offers>
      <offer id="221" org-id="806">
        <name lang="de">Medienmitteilungen des BAZL</name>
        <name lang="fr">Communiqués de presse de l'OFAC</name>
        <name lang="it">Comunicati stampa dell’UFAC</name>
        <name lang="en">Press releases from FOCA</name>
      </offer>
    </offers>
    <keywords>
      <keyword id="380" org-id="806">
        <name lang="de">Flughäfen</name>
        <name lang="fr">Aéroports</name>
        <name lang="it">Aeroporti</name>
        <name lang="en">Airports</name>
      </keyword>
      <keyword id="390" org-id="806">
        <name lang="de">Flugunfälle</name>
        <name lang="fr">Accidents d'aviation</name>
        <name lang="it">Infortuni aeronautici</name>
        <name lang="en">Aircraft Accidents</name>
      </keyword>
      <keyword id="800" org-id="806">
        <name lang="de">Luftfahrt: Sicherheit</name>
        <name lang="fr">Aviation : Sécurité technique</name>
        <name lang="it">Navigazione aerea: Sicurezza tecnica</name>
        <name lang="en">Aviation: Safety</name>
      </keyword>
      <keyword id="1510" org-id="806">
        <name lang="de">Luftfahrt</name>
        <name lang="fr">Aviation</name>
        <name lang="it">Aviazione</name>
        <name lang="en">Aviation</name>
      </keyword>
    </keywords>
    <topics>
      <topic id="46">
        <name lang="de">Verkehr</name>
        <name lang="fr">Transports</name>
        <name lang="it">Trasporti</name>
        <name lang="en">Transport</name>
      </topic>
    </topics>
  </message>
</messages>
