<?xml version="1.0" encoding="UTF-8"?>
<messages xmlns="https://www.news.admin.ch/messages" xmlns:xsi="http://www.w3.org/2001/XMLSchema-instance" version="1.0">
  <message id="70791" revoked="no">
    <version>1</version>
    <pubdate>2018-05-17</pubdate>
    <type>Memorandum</type>
    <originator department-msg="no" id="1084" lead="no" topnews="no">
      <department-id>501</department-id>
      <name lang="de">swisstopo – Bundesamt für Landestopografie</name>
      <name lang="fr">swisstopo – Office fédéral de topographie</name>
      <name lang="it">swisstopo – Ufficio federale di topografia</name>
      <name lang="en">swisstopo – Federal Office of Topography</name>
      <www lang="de">http://www.swisstopo.admin.ch</www>
      <www lang="fr">http://www.swisstopo.admin.ch</www>
      <www lang="it">http://www.swisstopo.admin.ch</www>
      <www lang="en">http://www.swisstopo.admin.ch</www>
      <email lang="de">info@swisstopo.ch</email>
      <email lang="fr">info@swisstopo.ch</email>
      <email lang="it">info@swisstopo.ch</email>
      <email lang="en">info@swisstopo.ch</email>
    </originator>
    <originator department-msg="yes" id="502" lead="yes" topnews="no">
      <department-id>501</department-id>
      <name lang="de">Generalsekretariat VBS</name>
      <name lang="fr">Secrétariat général du DDPS</name>
      <name lang="it">Segreteria generale del DDPS</name>
      <name lang="en">General Secretariat DDPS</name>
      <www lang="de">https://www.vbs.admin.ch/</www>
      <www lang="fr">https://www.vbs.admin.ch/</www>
      <www lang="it">https://www.vbs.admin.ch/</www>
      <www lang="en">https://www.vbs.admin.ch/</www>
      <email lang="de">postmaster.vbs@gs-vbs.admin.ch</email>
      <email lang="fr">postmaster.vbs@gs-vbs.admin.ch</email>
      <email lang="it">postmaster.vbs@gs-vbs.admin.ch</email>
      <email lang="en">postmaster.vbs@gs-vbs.admin.ch</email>
    </originator>
    <department id="501">
      <name lang="de">Eidgenössisches Departement für Verteidigung, Bevölkerungsschutz und Sport</name>
      <name lang="fr">Département fédéral de la défense, de la protection de la population et des sports</name>
      <name lang="it">Dipartimento federale della difesa, della protezione della popolazione e dello sport</name>
      <name lang="en">Federal Department of Defence, Civil Protection and Sports DDPS</name>
      <www lang="de">http://www.vbs.admin.ch</www>
      <www lang="fr">http://www.vbs.admin.ch</www>
      <www lang="it">http://www.vbs.admin.ch</www>
      <www lang="en">http://www.vbs.admin.ch</www>
      <email lang="de">kommunikation@gs-vbs.admin.ch</email>
      <email lang="fr">kommunikation@gs-vbs.admin.ch</email>
      <email lang="it">kommunikation@gs-vbs.admin.ch</email>
      <email lang="en">kommunikation@gs-vbs.admin.ch</email>
    </department>
    <content lang="de">
      <city>Bern</city>
      <title>Gemacht zum Wandern: Die neue Wanderkarte für die Schweiz</title>
      <lead>Rechtzeitig auf die neue Wandersaison haben das Bundesamt für Landestopografie swisstopo und die Schweizer Wanderwege die ersten sechzehn Blätter der neuen offiziellen Wanderkarte der Schweiz veröffentlicht. Dabei wurde die grafische Umsetzung von den Nutzerinnen und Nutzern massgeblich mitbestimmt.</lead>
      <text link="no">&lt;p&gt;Als Grundlage dient die neue Generation der Landeskarte 1:50 000. Diese wird seit Herbst 2016 im Zuge der Modernisierung des Landeskartenwerks eingeführt und bietet auch neue Möglichkeiten bei der Datenvisualisierung. So werden die thematischen Inhalte der Wanderkarte nun nicht mehr bloss auf die Grundkarte gelegt, sondern sie verschmelzen mit der topografischen Hintergrundinformation in einem Kartenbild zusammen. Das Resultat ist eine homogenere und besser lesbare Karte.&lt;/p&gt;&lt;h2&gt;Auf Bedürfnisse der Nutzerinnen und Nutzer abgestimmt&lt;/h2&gt;&lt;p&gt;swisstopo hat im Vorfeld verschiedene Darstellungsvarianten erarbeitet, verglichen und beurteilt. Ausschlaggebend für die jetzt vorliegende Variante war eine von swisstopo und den Schweizer Wanderwegen beim Publikum durchgeführte Online-Umfrage. Die auf der Karte dargestellten Wanderwege sind nun je nach Schwierigkeitsgrad in den Farben gelb, rot oder blau dargestellt, analog den im Gelände beschilderten drei Wegkategorien Wanderweg, Bergwanderweg und Alpinwanderweg.&lt;/p&gt;&lt;h2&gt;Handlicher und informativer&lt;/h2&gt;&lt;p&gt;Nebst der intuitiveren Darstellung erleichtern neu auch die beschrifteten ÖV-Haltestellen und Piktogramme zu Sehenswürdigkeiten oder abgelegenen Gasthöfen die Orientierung auf der Karte und im Gelände. Gekennzeichnet sind ebenso die nationalen und regionalen Wanderland-Routen von SchweizMobil.&lt;br /&gt;Mit einer Grösse von 11 x 22 cm ist die gefaltete Karte etwas schmäler und damit auch handlicher als das bisherige Format. Das strapazierfähige Papier ist wasser- und reissfest und gewährleistet eine lange Lebensdauer.&lt;br /&gt;Die neue Wanderkarte für die Schweiz ist eine Zusammenarbeit von swisstopo und dem Verband Schweizer Wanderwege. Die Schweizer Wanderwege sind auch für die Wandervorschläge mit Höhenprofil verantwortlich, die auf jedem Kartenblatt abgedruckt sind.&lt;/p&gt;&lt;p class="nsbtextkasten"&gt;&lt;strong&gt;Die erste Serie der neuen Wanderkarte für die Schweiz&lt;/strong&gt;&lt;br /&gt;Bis im Herbst 2020 werden alle 59 Einzelblätter der neuen Wanderkarte 1:50 000 vorliegen. Die jetzt erschienenen ersten 16 Kartenblätter decken hauptsächlich den Alpennordhang vom Greyerzerland bis ins Vorderrheintal sowie das zentrale Mittelland zwischen dem Oberaargau und der Linthebene ab. Folgende neue Blätter können ab sofort bezogen werden:&lt;br /&gt;&lt;br /&gt;224T Olten 237T Walenstadt 247T Sardona&lt;br /&gt;225T Zürich 242T Avenches 252T Bulle&lt;br /&gt;226T Rapperswil 243T Bern 253T Gantrisch&lt;br /&gt;234T Willisau 244T Escholzmatt 254T Interlaken&lt;br /&gt;235T Rotkreuz 245T Stans&lt;br /&gt;236T Lachen 246T Klausenpass&lt;/p&gt;</text>
      <contact>Ruedi Bösch Kommunikation swisstopo +41 58 469 01 27, ruedi.boesch@swisstopo.ch Thomas Gloor Bereichsleiter Wandern Schweizer Wanderwege +41 31 370 10 24, thomas.gloor@wandern.ch</contact>
      <attachment id="177807">
        <title>Kartentitel-237T_Walenstadt</title>
        <format>jpg</format>
        <size-kb>798</size-kb>
        <uri>https://www.newsd.admin.ch/newsd/message/attachments/52415.jpg</uri>
        <position>Context</position>
      </attachment>
      <attachment id="177808">
        <title>Kartentitel-242T_Avenches</title>
        <format>jpg</format>
        <size-kb>980</size-kb>
        <uri>https://www.newsd.admin.ch/newsd/message/attachments/52416.jpg</uri>
        <position>Context</position>
      </attachment>
      <attachment id="177809">
        <title>Kartentitel-254T_Interlaken</title>
        <format>jpg</format>
        <size-kb>777</size-kb>
        <uri>https://www.newsd.admin.ch/newsd/message/attachments/52417.jpg</uri>
        <position>Context</position>
      </attachment>
      <attachment id="177810">
        <title>Kartentitel-245T_Stans</title>
        <format>jpg</format>
        <size-kb>811</size-kb>
        <uri>https://www.newsd.admin.ch/newsd/message/attachments/52418.jpg</uri>
        <position>Context</position>
      </attachment>
      <attachment id="177811">
        <title>Kartentitel-253T_Gantrisch</title>
        <format>jpg</format>
        <size-kb>703</size-kb>
        <uri>https://www.newsd.admin.ch/newsd/message/attachments/52419.jpg</uri>
        <position>Context</position>
      </attachment>
      <attachment id="177812">
        <title>Kartenausschnitt_A6_254T-Grindelwald-First</title>
        <format>jpg</format>
        <size-kb>2294</size-kb>
        <uri>https://www.newsd.admin.ch/newsd/message/attachments/52420.jpg</uri>
        <position>Context</position>
      </attachment>
      <attachment id="177813">
        <title>Kartenausschnitt_A5_252T-Charmey</title>
        <format>jpg</format>
        <size-kb>4315</size-kb>
        <uri>https://www.newsd.admin.ch/newsd/message/attachments/52421.jpg</uri>
        <position>Context</position>
      </attachment>
      <attachment id="177814">
        <title>Kartenausschnitt_A7_242T-Areuse</title>
        <format>jpg</format>
        <size-kb>1109</size-kb>
        <uri>https://www.newsd.admin.ch/newsd/message/attachments/52422.jpg</uri>
        <position>Context</position>
      </attachment>
      <link id="177805">
        <title>swisstopo Onlineshop</title>
        <uri>https://shop.swisstopo.admin.ch/de/products/maps/leisure_maps/hiking_maps/hiking_maps50</uri>
        <position>Context</position>
      </link>
      <revisions> </revisions>
    </content>
    <content lang="fr">
      <city>Berne</city>
      <title>Conçue pour la randonnée : la nouvelle carte d’excursions pour la Suisse</title>
      <lead>Pour inaugurer la nouvelle saison de randonnée, l’Office fédéral de topographie swisstopo et Suisse Rando ont publié les seize premières feuilles des nouvelles cartes d’excursions officielles suisses. La représentation graphique a fortement été influencée par ses utilisateurs et ses utilisatrices.</lead>
      <text link="no">&lt;p&gt;La carte nationale à l’échelle 1:50 000 nouvelle génération sert de base. Cette dernière est introduite progressivement depuis l’automne 2016 dans le cadre de la modernisation des cartes nationales et offre également de nouvelles possibilités de visualisation des données. Le contenu thématique de la carte d’excursions n’est donc plus seulement superposé à la carte de base mais se fond en une unique représentation cartographique avec les informations topographiques de base. Le résultat : une carte plus homogène et plus lisible.&lt;/p&gt;&lt;h2&gt;Adaptée aux besoins des utilisateurs et utilisatrices&lt;/h2&gt;&lt;p&gt;swisstopo a élaboré, comparé et évalué plusieurs variantes de représentation au préalable. La décision a été influencée par un sondage en ligne que swisstopo et Suisse Rando ont réalisé auprès du public. Les chemins de randonnée figurant sur la carte sont désormais indiqués selon leur degré de difficulté. Tout comme les trois catégories de chemins de randonnée balisés existant sur le terrain (chemin de randonnée, chemin de randonnée de montagne et chemin de randonnée alpine), ils sont indiqués en jaune, en rouge ou en bleu.&lt;/p&gt;&lt;h2&gt;Plus pratique et instructive&lt;/h2&gt;&lt;p&gt;En plus de la présentation plus intuitive, les arrêts des transports publics et des pictogrammes représentant des lieux touristiques ou des auberges isolées sont également indiqués pour faciliter l'orientation sur la carte et sur le terrain. Les itinéraires nationaux et régionaux « La Suisse à pied » de SuisseMobile sont également marqués.&lt;br /&gt;Avec une dimension de 11 x 22 cm, la carte repliée est un peu moins large, et donc plus maniable, que l’ancien format. Le papier robuste résiste à l’eau et est indéchirable, ce qui lui garantit une longue durée de vie.&lt;br /&gt;La nouvelle carte d’excursions pour la Suisse est le fruit d’une collaboration entre swisstopo et l’association Suisse Rando. Cette dernière est aussi responsable des suggestions de chemins de randonnée avec profil altimétrique imprimées sur chaque feuille de carte.&lt;/p&gt;&lt;p class="nsbtextkasten"&gt;&lt;strong&gt;La première série des nouvelles cartes d’excursions pour la Suisse&lt;/strong&gt;&lt;br /&gt;D'ici l'automne 2020, les 59 feuilles de la nouvelle carte de randonnées à l’échelle 1:50 000 seront toutes disponibles. Les 16 premières cartes publiées dès maintenant couvrent principalement le versant nord des Alpes, de la Gruyère à la vallée antérieure du Rhin ainsi que le Plateau entre la Haute-Argovie et la plaine de la Linth. Les nouvelles feuilles suivantes sont maintenant disponibles à l'achat :&lt;br /&gt;&lt;br /&gt;224T Olten 237T Walenstadt 247T Sardona&lt;br /&gt;225T Zürich 242T Avenches 252T Bulle&lt;br /&gt;226T Rapperswil 243T Bern 253T Gantrisch&lt;br /&gt;234T Willisau 244T Escholzmatt 254T Interlaken&lt;br /&gt;235T Rotkreuz 245T Stans&lt;br /&gt;236T Lachen 246T Klausenpass&lt;/p&gt;</text>
      <contact>Ruedi Bösch communication swisstopo +41 58 469 01 27 ruedi.boesch@swisstopo.ch Thomas Gloor responsable de la section randonnée Suisse Rando +41 31 370 10 24 thomas.gloor@wandern.ch</contact>
      <attachment id="177807">
        <title>Kartentitel-237T_Walenstadt</title>
        <format>jpg</format>
        <size-kb>798</size-kb>
        <uri>https://www.newsd.admin.ch/newsd/message/attachments/52415.jpg</uri>
        <position>Context</position>
      </attachment>
      <attachment id="177808">
        <title>Kartentitel-242T_Avenches</title>
        <format>jpg</format>
        <size-kb>980</size-kb>
        <uri>https://www.newsd.admin.ch/newsd/message/attachments/52416.jpg</uri>
        <position>Context</position>
      </attachment>
      <attachment id="177809">
        <title>Kartentitel-254T_Interlaken</title>
        <format>jpg</format>
        <size-kb>777</size-kb>
        <uri>https://www.newsd.admin.ch/newsd/message/attachments/52417.jpg</uri>
        <position>Context</position>
      </attachment>
      <attachment id="177810">
        <title>Kartentitel-245T_Stans</title>
        <format>jpg</format>
        <size-kb>811</size-kb>
        <uri>https://www.newsd.admin.ch/newsd/message/attachments/52418.jpg</uri>
        <position>Context</position>
      </attachment>
      <attachment id="177811">
        <title>Kartentitel-253T_Gantrisch</title>
        <format>jpg</format>
        <size-kb>703</size-kb>
        <uri>https://www.newsd.admin.ch/newsd/message/attachments/52419.jpg</uri>
        <position>Context</position>
      </attachment>
      <attachment id="177812">
        <title>Kartenausschnitt_A6_254T-Grindelwald-First</title>
        <format>jpg</format>
        <size-kb>2294</size-kb>
        <uri>https://www.newsd.admin.ch/newsd/message/attachments/52420.jpg</uri>
        <position>Context</position>
      </attachment>
      <attachment id="177813">
        <title>Kartenausschnitt_A5_252T-Charmey</title>
        <format>jpg</format>
        <size-kb>4315</size-kb>
        <uri>https://www.newsd.admin.ch/newsd/message/attachments/52421.jpg</uri>
        <position>Context</position>
      </attachment>
      <attachment id="177814">
        <title>Kartenausschnitt_A7_242T-Areuse</title>
        <format>jpg</format>
        <size-kb>1109</size-kb>
        <uri>https://www.newsd.admin.ch/newsd/message/attachments/52422.jpg</uri>
        <position>Context</position>
      </attachment>
      <link id="177806">
        <title>Boutique en ligne swisstopo</title>
        <uri>https://shop.swisstopo.admin.ch/fr/products/maps/leisure_maps/hiking_maps/hiking_maps50</uri>
        <position>Context</position>
      </link>
      <revisions> </revisions>
    </content>
    <content lang="it">
      <city>Berna</city>
      <title>Concepita per le escursioni: la nuova carta escursionistica per la Svizzera</title>
      <lead>Puntualmente per la nuova stagione escursionistica, l’Ufficio federale di topografia swisstopo e Sentieri Svizzeri hanno pubblicato i primi sedici fogli della nuova carta escursionistica ufficiale della Svizzera. Alla realizzazione grafica hanno contribuito fortemente gli utenti.</lead>
      <text link="no">&lt;p&gt;Come base funge la nuova generazione della carta nazionale 1:50 000, introdotta progressi-vamente dall’autunno 2016 nel quadro della modernizzazione dell’opera cartografica nazio-nale e che offre anche nuove possibilità di visualizzazione dei dati. Così, i contenuti tematici della carta escursionistica non saranno più semplicemente piazzati sulla carta di base, ma si fondono con le informazioni topografiche di contesto in un’unica immagine cartografica. Il risultato è una carta più omogenea e più leggibile.&lt;/p&gt;&lt;h2&gt;Adeguata alle esigenze degli utenti&lt;/h2&gt;&lt;p&gt;In una prima fase, swisstopo ha elaborato, confrontato e valutato diverse possibilità di rappresentazione. A favore della variante attuale si è pronunciato il pubblico in un sondaggio online di swisstopo e di Sentieri Svizzeri. I sentieri escursionistici ripresi sulla carta sono ora rappresentati nei colori giallo, rosso o blu a seconda del grado di difficoltà, analogamente alle tre categorie «sentiero escursionistico», «sentiero escursionistico di montagna» e «sentiero escursionistico alpino» indicate sul territorio.&lt;/p&gt;&lt;h2&gt;Più pratica e informativa&lt;/h2&gt;&lt;p&gt;Oltre alla rappresentazione intuitiva, anche l’indicazione delle fermate dei mezzi di trasporto pubblici e i pittogrammi relativi ai punti di interesse o agli alberghi isolati semplificano ora l’orientamento sulla carta e sul territorio. Sono indicati anche i percorsi regionali e nazionali «La Svizzera a piedi» di SvizzeraMobile.&lt;br /&gt;Con una misura di 11 x 22 cm, la carta piegata è leggermente più stretta e quindi più pratica rispetto al formato precedente. La carta resistente all’acqua e allo strappo garantisce una lunga durata.&lt;br /&gt;La nuova carta escursionistica della Svizzera nasce dalla collaborazione tra swisstopo e l’associazione Sentieri Svizzeri. Sentieri Svizzeri è responsabile anche delle proposte escur-sionistiche con profilo altimetrico stampate su ogni foglio della carta.&lt;/p&gt;&lt;p class="nsbtextkasten"&gt;&lt;strong&gt;La prima serie della nuova carta escursionistica per la Svizzera&lt;/strong&gt;&lt;br /&gt;Entro l’autunno 2020 saranno disponibili tutti i 59 fogli singoli della nuova carta escursio¬nistica 1:50 000. I primi 16 fogli della carta apparsi finora coprono soprattutto il versante settentrionale delle Alpi dal distretto della Gruyère alla valle del Reno anteriore, oltre all’Altipiano svizzero centrale tra l’Alta Argovia e la pianura della Linth. Da subito sono acquistabili i seguenti nuovi fogli:&lt;br /&gt;&lt;br /&gt;224T Olten 237T Walenstadt 247T Sardona&lt;br /&gt;225T Zürich 242T Avenches 252T Bulle&lt;br /&gt;226T Rapperswil 243T Bern 253T Gantrisch&lt;br /&gt;234T Willisau 244T Escholzmatt 254T Interlaken&lt;br /&gt;235T Rotkreuz 245T Stans&lt;br /&gt;236T Lachen 246T Passo del Klausen&lt;/p&gt;</text>
      <contact>Ruedi Bösch Comunicazione swisstopo +41 58 469 01 27, ruedi.boesch@swisstopo.ch Thomas Gloor Capo-settore Escursioni Sentieri Svizzeri +41 31 370 10 24, thomas.gloor@wandern.ch</contact>
      <attachment id="177807">
        <title>Kartentitel-237T_Walenstadt</title>
        <format>jpg</format>
        <size-kb>798</size-kb>
        <uri>https://www.newsd.admin.ch/newsd/message/attachments/52415.jpg</uri>
        <position>Context</position>
      </attachment>
      <attachment id="177808">
        <title>Kartentitel-242T_Avenches</title>
        <format>jpg</format>
        <size-kb>980</size-kb>
        <uri>https://www.newsd.admin.ch/newsd/message/attachments/52416.jpg</uri>
        <position>Context</position>
      </attachment>
      <attachment id="177809">
        <title>Kartentitel-254T_Interlaken</title>
        <format>jpg</format>
        <size-kb>777</size-kb>
        <uri>https://www.newsd.admin.ch/newsd/message/attachments/52417.jpg</uri>
        <position>Context</position>
      </attachment>
      <attachment id="177810">
        <title>Kartentitel-245T_Stans</title>
        <format>jpg</format>
        <size-kb>811</size-kb>
        <uri>https://www.newsd.admin.ch/newsd/message/attachments/52418.jpg</uri>
        <position>Context</position>
      </attachment>
      <attachment id="177811">
        <title>Kartentitel-253T_Gantrisch</title>
        <format>jpg</format>
        <size-kb>703</size-kb>
        <uri>https://www.newsd.admin.ch/newsd/message/attachments/52419.jpg</uri>
        <position>Context</position>
      </attachment>
      <attachment id="177812">
        <title>Kartenausschnitt_A6_254T-Grindelwald-First</title>
        <format>jpg</format>
        <size-kb>2294</size-kb>
        <uri>https://www.newsd.admin.ch/newsd/message/attachments/52420.jpg</uri>
        <position>Context</position>
      </attachment>
      <attachment id="177813">
        <title>Kartenausschnitt_A5_252T-Charmey</title>
        <format>jpg</format>
        <size-kb>4315</size-kb>
        <uri>https://www.newsd.admin.ch/newsd/message/attachments/52421.jpg</uri>
        <position>Context</position>
      </attachment>
      <attachment id="177814">
        <title>Kartenausschnitt_A7_242T-Areuse</title>
        <format>jpg</format>
        <size-kb>1109</size-kb>
        <uri>https://www.newsd.admin.ch/newsd/message/attachments/52422.jpg</uri>
        <position>Context</position>
      </attachment>
      <link id="177804">
        <title>Negozio online swisstopo</title>
        <uri>https://shop.swisstopo.admin.ch/it/products/maps/leisure_maps/hiking_maps/hiking_maps50</uri>
        <position>Context</position>
      </link>
      <revisions> </revisions>
    </content>
    <keywords>
      <keyword id="5360" org-id="502">
        <name lang="de">Technologie / Wissenschaft / Forschung</name>
        <name lang="fr">Technologies / Sciences / Recherche</name>
        <name lang="it">Tecnologia / Scienza / Ricerca</name>
        <name lang="en">Technology / Science / Research</name>
      </keyword>
      <keyword id="5410" org-id="502">
        <name lang="de">Kartografie</name>
        <name lang="fr">Cartographie</name>
        <name lang="it">Cartografia</name>
        <name lang="en">Cartography</name>
      </keyword>
      <keyword id="5610" org-id="502">
        <name lang="de">Entwicklung / Planung / Reform</name>
        <name lang="fr">Développement / Planification / Réforme</name>
        <name lang="it">Sviluppo / Pianificazione / Riforma</name>
        <name lang="en">development / planning / reform</name>
      </keyword>
      <keyword id="5820" org-id="502">
        <name lang="de">Infrastruktur</name>
        <name lang="fr">Infrastructure</name>
        <name lang="it">Infrastruttura</name>
        <name lang="en">infrastructure</name>
      </keyword>
    </keywords>
    <topics>
      <topic id="27">
        <name lang="de">Reisen und Tourismus</name>
        <name lang="fr">Voyages et tourisme</name>
        <name lang="it">Viaggi e turismo</name>
        <name lang="en">Travel and Tourism</name>
      </topic>
    </topics>
  </message>
</messages>
